senaps_sensor/__init__.py
senaps_sensor/api.py
senaps_sensor/auth.py
senaps_sensor/binder.py
senaps_sensor/const.py
senaps_sensor/error.py
senaps_sensor/models.py
senaps_sensor/parsers.py
senaps_sensor/utils.py
senaps_sensor/vocabulary.py
eratos_sensor-2.17.0.dist-info/METADATA
eratos_sensor-2.17.0.dist-info/WHEEL
eratos_sensor-2.17.0.dist-info/licenses/LICENSE
eratos_sensor-2.17.0.dist-info/RECORD
