Metadata-Version: 2.4
Name: eratos-sensor
Version: 2.17.0
Summary: Senaps Sensor Data API Client
Project-URL: Homepage, https://bitbucket.csiro.au/projects/SC/repos/sensor-api-python-client/browse
Author-email: CSIRO Data61 <senaps@csiro.au>
Maintainer-email: Eratos <support@eratos.com>
License: MIT License
License-File: LICENSE
Keywords: api,client,library,senaps,sensor
Classifier: Development Status :: 4 - Beta
Classifier: License :: OSI Approved :: MIT License
Classifier: Operating System :: OS Independent
Classifier: Programming Language :: Python
Classifier: Programming Language :: Python :: 3.7
Classifier: Programming Language :: Python :: 3.8
Classifier: Programming Language :: Python :: 3.9
Classifier: Programming Language :: Python :: 3.10
Classifier: Programming Language :: Python :: 3.11
Classifier: Programming Language :: Python :: 3.12
Classifier: Topic :: Software Development :: Libraries
Requires-Python: >=3.7
Requires-Dist: enum34; python_version < '3.4.0'
Requires-Dist: requests<3.0.0,>=2.22.0
Requires-Dist: six>=1.7.3
